vaxbnana/__init__.py
vaxbnana/_utils.py
vaxbnana/_version.py
vaxbnana/base.py
vaxbnana/clash.py
vaxbnana/clashmeta.py
vaxbnana/data.py
vaxbnana/exceptions.py
vaxbnana/links.py
vaxbnana/singbox.py
vaxbnana/wireguard.py
vaxbnana/xray.py
vaxbnana/templates/clash.yml
vaxbnana/templates/singbox.json
vaxbnana/templates/xray.json
vaxbnana/templates/xray_mux.json
vaxbnana-0.1.3.dist-info/METADATA
vaxbnana-0.1.3.dist-info/WHEEL
vaxbnana-0.1.3.dist-info/RECORD
