Metadata-Version: 2.4
Name: vaxbnana
Version: 0.1.3
Summary: generate configurations painlessly for xray/sing-box/clash
Project-URL: Homepage, https://github.com/benhomlxs/vaxbnana
Project-URL: Repository, https://github.com/benhomlxs/vaxbnana.git
Project-URL: Issues, https://github.com/benhomlxs/vaxbnana/issues
Author-email: Ben <ben@duck.com>
Maintainer-email: Ben <ben@duck.com>
Requires-Python: >=3.9
Requires-Dist: pyyaml>=6.0.1
